{
  "date": "2026-06-20",
  "market_dir": "F:/ai/qclaw-output/market-sample",
  "market_meta": "F:/ai/qclaw-output/market-sample-meta.json",
  "items": "F:/ai/qclaw-output/finance-daily-items-sample-2026-06-20.jsonl",
  "output_dir": "F:/ai/qclaw-output",
  "min_bars": 30,
  "strategy": "optimize",
  "account_equity": 100000,
  "risk_per_trade": 0.005,
  "max_position_pct": 0.2,
  "max_total_exposure": 0.6,
  "max_theme_exposure_pct": 0.35,
  "atr_multiple": 2.0,
  "min_score": 15,
  "risk_state": "F:/ai/qclaw-output/finance-risk-state.json",
  "quality_check": true,
  "quality_min_score": 70,
  "quality_max_gap_business_days": 10,
  "quality_max_abs_return": 0.35,
  "signal_scorecard": "F:/ai/qclaw-output/finance-signal-scorecard.json",
  "market_index_csv": "F:/ai/qclaw-output/finance-market-index-sample.csv",
  "market_breadth": "F:/ai/qclaw-output/finance-market-breadth-sample.json",
  "ingest": false,
  "brain_url": "http://localhost:8766"
}
