{
  "id": "task_20260706_knowledge_brain_evolution",
  "title": "智慧大脑进化路线图",
  "description": "按照研究计划开始实现智慧大脑的进化功能",
  "source": "codex",
  "priority": "high",
  "status": "in_progress",
  "created_at": "2026-07-06T02:45:00+08:00",
  "phases": [
    {
      "name": "阶段一：基础增强",
      "tasks": [
        {"name": "原子化知识节点", "priority": "P0", "status": "pending"},
        {"name": "双向链接系统", "priority": "P0", "status": "pending"},
        {"name": "知识分类体系", "priority": "P0", "status": "pending"},
        {"name": "时间线索引", "priority": "P1", "status": "pending"}
      ],
      "target_date": "2026-07-20"
    },
    {
      "name": "阶段二：记忆强化",
      "tasks": [
        {"name": "间隔复习系统", "priority": "P0", "status": "pending"},
        {"name": "重要度评分", "priority": "P0", "status": "pending"},
        {"name": "遗忘曲线建模", "priority": "P1", "status": "pending"},
        {"name": "记忆强度追踪", "priority": "P1", "status": "pending"}
      ],
      "target_date": "2026-08-03"
    },
    {
      "name": "阶段三：决策增强",
      "tasks": [
        {"name": "决策树推理", "priority": "P0", "status": "pending"},
        {"name": "情景模拟", "priority": "P1", "status": "pending"},
        {"name": "后果推演", "priority": "P1", "status": "pending"},
        {"name": "多方案评估", "priority": "P1", "status": "pending"}
      ],
      "target_date": "2026-08-17"
    },
    {
      "name": "阶段四：高级认知",
      "tasks": [
        {"name": "跨领域联想", "priority": "P0", "status": "pending"},
        {"name": "隐藏模式发现", "priority": "P0", "status": "pending"},
        {"name": "元认知监控", "priority": "P1", "status": "pending"},
        {"name": "主动知识获取", "priority": "P2", "status": "pending"}
      ],
      "target_date": "2026-08-31"
    },
    {
      "name": "阶段五：长期演化",
      "tasks": [
        {"name": "自我进化机制", "priority": "P0", "status": "pending"},
        {"name": "知识蒸馏", "priority": "P1", "status": "pending"},
        {"name": "知识融合", "priority": "P2", "status": "pending"},
        {"name": "遗忘管理", "priority": "P2", "status": "pending"}
      ],
      "target_date": "2026-09-14"
    }
  ],
  "milestones": [
    {"name": "M1: 原子化知识", "date": "2026-07-20"},
    {"name": "M2: 双向链接", "date": "2026-07-27"},
    {"name": "M3: 复习系统", "date": "2026-08-03"},
    {"name": "M4: 决策支持", "date": "2026-08-17"},
    {"name": "M5: 高级认知", "date": "2026-08-31"},
    {"name": "M6: 自我进化", "date": "2026-09-14"}
  ],
  "references": [
    "super-jarvis/board/tasks/shared/knowledge_brain_research_plan.md"
  ]
}